LICENSE
README.md
setup.py
img_base64/__init__.py
img_base64.egg-info/PKG-INFO
img_base64.egg-info/SOURCES.txt
img_base64.egg-info/dependency_links.txt
img_base64.egg-info/top_level.txt