Metadata-Version: 2.1
Name: img-base64
Version: 0.0.1
Summary: 调用此方法可将图片转为base64格式
Home-page: https://github.com/yuanyunqiang
Author: 袁运强
Author-email: 6497569033@qq.com
License: UNKNOWN
Platform: UNKNOWN
Classifier: Programming Language :: Python :: 3
Classifier: License :: OSI Approved :: MIT License
Classifier: Operating System :: OS Independent
Requires-Python: >=3.6
License-File: LICENSE
